pip_versions/__init__.py
pip_versions/cli.py
pip_versions/core.py
pip_versions-0.1.0.dist-info/entry_points.txt
pip_versions-0.1.0.dist-info/WHEEL
pip_versions-0.1.0.dist-info/METADATA
pip_versions-0.1.0.dist-info/RECORD
