Metadata-Version: 2.1
Name: pip-versions
Version: 0.1.0
Summary: Show pip version information from pypi
Home-page: https://github.com/willemt/pip-versions/
Keywords: pip
Author: Willem Thiart
Author-email: himself@willemthiart.com
Requires-Python: >=3.7,<4.0
Classifier: Programming Language :: Python :: 3
Classifier: Programming Language :: Python :: 3.7
Classifier: Programming Language :: Python :: 3.8
Requires-Dist: cliar (>=1.3.4,<2.0.0)
Project-URL: Repository, https://github.com/willemt/pip-versions/
